{
  "name": "Aeon Summon",
  "bg_color": "#111827",
  "card_color": "#1f2937",
  "accent_color": "#f97316",
  "accent_hover": "#fb923c",
  "text_color": "#f0f9ff",
  "text_dim": "#9ca3af",
  "border_color": "#374151",
  "success_color": "#06b6d4",
  "error_color": "#f43f5e",
  "btn_accept_bg": "#ea580c",
  "btn_accept_fg": "#f0f9ff",
  "btn_accept_hover": "#f97316",
  "btn_success_bg": "#0891b2",
  "btn_success_fg": "#f0f9ff",
  "btn_success_hover": "#06b6d4",
  "btn_caution_bg": "#be123c",
  "btn_caution_fg": "#f0f9ff",
  "btn_caution_hover": "#e11d48",
  "btn_utility_bg": "#1f2937",
  "btn_utility_fg": "#f97316",
  "btn_utility_hover": "#374151"
}
